django_mc2p/__init__.py
django_mc2p/admin.py
django_mc2p/apps.py
django_mc2p/constants.py
django_mc2p/models.py
django_mc2p/signals.py
django_mc2p/urls.py
django_mc2p/views.py
django_mc2p/migrations/0001_initial.py
django_mc2p/migrations/0002_auto_20171204_1547.py
django_mc2p/migrations/__init__.py
mc2p_django-0.1.3.dist-info/DESCRIPTION.rst
mc2p_django-0.1.3.dist-info/LICENSE.txt
mc2p_django-0.1.3.dist-info/METADATA
mc2p_django-0.1.3.dist-info/metadata.json
mc2p_django-0.1.3.dist-info/RECORD
mc2p_django-0.1.3.dist-info/top_level.txt
mc2p_django-0.1.3.dist-info/WHEEL
