Metadata-Version: 2.0
Name: mc2p-django
Version: 0.1.3
Summary: MyChoice2Pay Django Bindings
Home-page: https://github.com/mc2p/mc2p-django
Author: MyChoice2Pay
Author-email: support@mychoice2pay.com
License: BSD
Download-URL: https://github.com/mc2p/mc2p-django/archive/v0.1.3.tar.gz
Keywords: mychoice2pay,payments
Platform: UNKNOWN
Classifier: Intended Audience :: Developers
Classifier: License :: OSI Approved :: BSD License
Classifier: Operating System :: OS Independent
Classifier: Programming Language :: Python
Classifier: Programming Language :: Python :: 2
Classifier: Programming Language :: Python :: 2.7
Classifier: Programming Language :: Python :: 3
Classifier: Programming Language :: Python :: 3.3
Classifier: Programming Language :: Python :: 3.4
Classifier: Programming Language :: Python :: 3.5
Classifier: Programming Language :: Python :: 3.6
Classifier: Programming Language :: Python :: Implementation :: PyPy
Classifier: Topic :: Software Development :: Libraries :: Python Modules
Requires-Dist: django
Requires-Dist: mc2p-python
